README
setup.cfg
setup.py
oe_lite.egg-info/PKG-INFO
oe_lite.egg-info/SOURCES.txt
oe_lite.egg-info/dependency_links.txt
oe_lite.egg-info/entry_points.txt
oe_lite.egg-info/not-zip-safe
oe_lite.egg-info/top_level.txt
oebakery/__init__.py
oebakery/data.py
oebakery/log.py
oebakery/oe.py
oebakery/parse.py
oebakery/path.py
oebakery/shell.py
oebakery/cmd/__init__.py
oebakery/cmd/bake.py
oebakery/cmd/clone.py
oebakery/cmd/cmds.py
oebakery/cmd/init.py
oebakery/cmd/pull.py
oebakery/cmd/show.py
oebakery/cmd/update.py