Metadata-Version: 1.0
Name: oe-lite
Version: 4.0.2
Summary: OE-lite - embedded Linux platform development kit
Home-page: http://oe-lite.org/
Author: Esben Haabendal
Author-email: esben.haabendal@prevas.dk
License: GPL
Platform: UNKNOWN
